markdown_strings/__init__.py
markdown_strings-3.4.0.dist-info/LICENSE.txt
markdown_strings-3.4.0.dist-info/METADATA
markdown_strings-3.4.0.dist-info/WHEEL
markdown_strings-3.4.0.dist-info/top_level.txt
markdown_strings-3.4.0.dist-info/RECORD
