Metadata-Version: 2.1
Name: markdown-strings
Version: 3.4.0
Summary: Create markdown formatted text
Home-page: https://github.com/awesmubarak/markdown_strings
Author: Awes Mubarak
Author-email: contact@awesmubarak.com
License: MIT
Keywords: markdown md
Platform: UNKNOWN
Classifier: Development Status :: 5 - Production/Stable
Classifier: Intended Audience :: Developers
Classifier: Operating System :: OS Independent
Classifier: Topic :: Text Processing :: Markup
Classifier: License :: OSI Approved :: MIT License
Classifier: Programming Language :: Python
License-File: LICENSE.txt
